{
  "NO": 1,
  "TITLE": "Sample Quiz Title",
  "PARAGRAPH": "This is a sample paragraph that outlines a topic in detail. It provides information and context for the related questions.",
  "questions": [
    {
      "Question": "What is the main idea of the paragraph?",
      "OptionA": "A. Option one",
      "OptionB": "B. Option two",
      "OptionC": "C. Option three",
      "OptionD": "D. Option four",
      "Answer": "B"
    },
    {
      "Question": "Which aspect does the paragraph emphasize?",
      "OptionA": "A. Aspect one",
      "OptionB": "B. Aspect two",
      "OptionC": "C. Aspect three",
      "OptionD": "D. Aspect four",
      "Answer": "D"
    }
  ]
}
